[
  {
    "property": "randommods.remove-reset-slash",
    "type": "checkbox",
    "label": "Remove Reset Slash From Pinned Tabs",
    "default": "true"
  },

  {
    "property": "randommods.clean-tabs-archive-icon",
    "type": "checkbox",
    "label": "Clean Tabs Archive Icon",
    "default": "true"
  },

  {
    "property": "randommods.quicktabs-tweak",
    "type": "checkbox",
    "label": "Quick Tabs Tweak",
    "default": "true"
  },

  {
    "property": "randommods.quicktabs-icon-only",
    "type": "checkbox",
    "label": "Quick Tabs Icon Only",
    "default": "true"
  },

  {
    "property": "randommods.minor-workspace-indicator-tweak",
    "type": "checkbox",
    "label": "Minor Workspace Indicator Tweak",
    "default": "true"
  },

  {
    "property": "randommods.nebula-miniplayer-margin-tweak",
    "type": "checkbox",
    "label": "Nebula Miniplayer Margin Tweak",
    "default": "true"
  },

  {
    "property": "randommods.tab-throbber-loading-circle",
    "type": "checkbox",
    "label": "Enable Spinner Animation for Tab Loading Indicator",
    "default": "true"
  },

  {
    "property": "randommods.change-copy-url-ext-adressbar-icon",
    "type": "checkbox",
    "label": "Change Copy URL Extension Icon on Address Bar",
    "default": "true"
  },

  {
    "property": "randommods.hide-overflow-button",
    "type": "checkbox",
    "label": "Hide Overflow Button",
    "default": "true"
  },

  {
    "property": "randommods.show-pageaction-in-urlbar",
    "type": "checkbox",
    "label": "Show Page Action Icons in Address Bar",
    "default": "true"
  },

  {
    "property": "randommods.panelview-noborder",
    "type": "checkbox",
    "label": "Remove Border from Panel View",
    "default": "true"
  }
]
